chatbilly/__init__.py
chatbilly/api.py
chatbilly/cli.py
chatbilly/core.py
chatbilly/templates/Dockerfile
chatbilly/templates/index.html
chatbilly/templates/prompt.txt
chatbilly-0.0.1.dist-info/entry_points.txt
chatbilly-0.0.1.dist-info/LICENSE
chatbilly-0.0.1.dist-info/WHEEL
chatbilly-0.0.1.dist-info/METADATA
chatbilly-0.0.1.dist-info/RECORD
